README.md
setup.py
ikflow/__init__.py
ikflow/config.py
ikflow/ikflow_solver.py
ikflow/math_utils.py
ikflow/model.py
ikflow/model_descriptions.yaml
ikflow/model_loading.py
ikflow/supporting_types.py
ikflow/utils.py
ikflow/visualizations.py
ikflow.egg-info/PKG-INFO
ikflow.egg-info/SOURCES.txt
ikflow.egg-info/dependency_links.txt
ikflow.egg-info/requires.txt
ikflow.egg-info/top_level.txt
ikflow/visualization_resources/klampt_resources/objects/README.md
ikflow/visualization_resources/klampt_resources/objects/block.obj
ikflow/visualization_resources/klampt_resources/objects/block_small.obj
ikflow/visualization_resources/klampt_resources/objects/convert.sh
ikflow/visualization_resources/klampt_resources/objects/cube.geom
ikflow/visualization_resources/klampt_resources/objects/cylinder.obj
ikflow/visualization_resources/klampt_resources/objects/flatblock.obj
ikflow/visualization_resources/klampt_resources/objects/flatblock2.obj
ikflow/visualization_resources/klampt_resources/objects/flatblock3.obj
ikflow/visualization_resources/klampt_resources/objects/flatblock4.obj
ikflow/visualization_resources/klampt_resources/objects/flatblock5.obj
ikflow/visualization_resources/klampt_resources/objects/mug.obj
ikflow/visualization_resources/klampt_resources/objects/mug_klampt.obj
ikflow/visualization_resources/klampt_resources/objects/sphere.geom
ikflow/visualization_resources/klampt_resources/objects/sphere.obj
ikflow/visualization_resources/klampt_resources/objects/sphere_10cm.obj
ikflow/visualization_resources/klampt_resources/objects/sphere_5cm.obj
ikflow/visualization_resources/klampt_resources/objects/srimugsmooth.obj
ikflow/visualization_resources/klampt_resources/objects/claraio_downloads/mug.mlp
ikflow/visualization_resources/klampt_resources/objects/claraio_downloads/mug.obj
ikflow/visualization_resources/klampt_resources/terrains/plane.env