Metadata-Version: 2.1
Name: ikflow
Version: 0.0.8
Summary: Open source implementation of the 'IKFlow' inverse kinematics solver
Home-page: https://github.com/jstmn/ikflow
Author: Jeremy Morgan
Author-email: jsmorgan6@gmail.com
License: LICENSE.txt
Platform: UNKNOWN
Provides-Extra: dev
